aescryptox/__init__.py
aescryptox/aes.py
aescryptox/filecrypto.py
aescryptox/hmac_sha256.py
aescryptox/keywrap.py
aescryptox/modes.py
aescryptox/utils.py
aescryptox-0.0.1.dist-info/METADATA
aescryptox-0.0.1.dist-info/WHEEL
aescryptox-0.0.1.dist-info/top_level.txt
aescryptox-0.0.1.dist-info/RECORD
