Metadata-Version: 2.4
Name: aescryptox
Version: 0.0.1
Summary: Pure Python AES encryption library supporting ECB, CBC, PCBC, CTR, GCM, CCM, XTS, SIV, EAX, OCB3, OFB, CFB, with file encryption and HMAC.
Home-page: https://github.com/Athallah1234/AESCryptoX
Author: ATHALLAH RAJENDRA PUTRA JUNIARTO
Author-email: youremail@example.com
Classifier: Programming Language :: Python :: 3
Classifier: Topic :: Security :: Cryptography
Requires-Python: >=3.7
Dynamic: author
Dynamic: author-email
Dynamic: classifier
Dynamic: description
Dynamic: description-content-type
Dynamic: home-page
Dynamic: requires-python
Dynamic: summary
